Metadata-Version: 2.1
Name: kofiko
Version: 1.0.5
Summary: Code-First Configuration package for Python
Home-page: https://github.com/davidohana/kofiko
Author: David Ohana, IBM Research Haifa
Author-email: david.ohana@ibm.com
License: Apache
Keywords: configuration,code,first,config,ini,environment,env,IBM
Platform: UNKNOWN
Classifier: Programming Language :: Python :: 3.6
Classifier: Programming Language :: Python :: 3.7
Classifier: License :: OSI Approved :: Apache Software License
Classifier: Operating System :: OS Independent
Classifier: Topic :: Software Development :: Libraries
